fhr.py
fhr-0.1.1.dist-info/LICENSE
fhr-0.1.1.dist-info/METADATA
fhr-0.1.1.dist-info/WHEEL
fhr-0.1.1.dist-info/entry_points.txt
fhr-0.1.1.dist-info/RECORD
