Metadata-Version: 2.1
Name: fhr
Version: 0.1.1
Summary: This tool is used to validate and convert between different FHR header serializations
License: USDA-ARS
Author: David Molik
Author-email: david.molik@usda.gov
Requires-Python: >=3.9,<4.0
Classifier: License :: Other/Proprietary License
Classifier: Programming Language :: Python :: 3
Classifier: Programming Language :: Python :: 3.9
Classifier: Programming Language :: Python :: 3.10
Classifier: Programming Language :: Python :: 3.11
Classifier: Programming Language :: Python :: 3.12
Requires-Dist: argparse (>=1.4.0,<2.0.0)
Requires-Dist: jsonschema (>=4.21.1,<5.0.0)
Requires-Dist: microdata (>=0.8.0,<0.9.0)
Requires-Dist: pyyaml (>=6.0.1,<7.0.0)
